mpv_whisper/__init__.py
mpv_whisper/__main__.py
mpv_whisper/audio.py
mpv_whisper/cli.py
mpv_whisper/config.py
mpv_whisper/config.toml
mpv_whisper/monitor.py
mpv_whisper/subtitle.py
mpv_whisper/transcribe.py
mpv_whisper-0.1.4.dist-info/entry_points.txt
mpv_whisper-0.1.4.dist-info/METADATA
mpv_whisper-0.1.4.dist-info/WHEEL
mpv_whisper-0.1.4.dist-info/RECORD
