Metadata-Version: 2.1
Name: mpv-whisper
Version: 0.1.4
Summary: Enhances a local MPV instance with Whisper transcription capabilities
Home-page: https://github.com/alexkoay/mpv-whisper
Author: Alex Koay
Author-email: alexkoay88@gmail.com
Requires-Python: >=3.9,<4.0
Classifier: License :: OSI Approved :: MIT License
Classifier: Operating System :: OS Independent
Classifier: Programming Language :: Python :: 3
Classifier: Programming Language :: Python :: 3.9
Classifier: Programming Language :: Python :: 3.10
Classifier: Programming Language :: Python :: 3.11
Classifier: Programming Language :: Python :: 3.12
Requires-Dist: attrs (>=23.2.0,<24.0.0)
Requires-Dist: cattrs (>=23.2.3,<24.0.0)
Requires-Dist: faster-whisper (>=1.0.1,<2.0.0)
Requires-Dist: more_itertools (>=10.2.0,<11.0.0)
Requires-Dist: numpy (>=1.26.4,<2.0.0)
Requires-Dist: pyav (>=12.0.4,<13.0.0)
Requires-Dist: python_mpv_jsonipc (>=1.2.0,<2.0.0)
Requires-Dist: toml (>=0.10.2,<0.11.0)
Project-URL: Repository, https://github.com/alexkoay/mpv-whisper
